[
  {
    "codigo": "7896024761408",
    "nome": "Biscoito Piraque recheado supreme limão",
    "validade": "2025-06-08",
    "imagem": "https://images.openfoodfacts.org/images/products/789/602/476/1408/front_en.3.400.jpg"
  },
  {
    "codigo": "7896024761842",
    "nome": "Biscoito Cookies Piraque - Goiabinha Original 80g",
    "validade": "2025-06-15",
    "imagem": "/static/uploads/7896024761842.png"
  },
  {
    "codigo": "7896024761828",
    "nome": "Biscoito Cookies Piraque - Leite Maltado Black 80g",
    "validade": "2025-06-05",
    "imagem": "/static/uploads/7896024761828.png"
  },
  {
    "codigo": "7891203058164",
    "nome": "Panco - Biscoito de Leite 200g",
    "validade": "2025-06-27",
    "imagem": "/static/uploads/7891203058164.png"
  },
  {
    "codigo": "7891962054100",
    "nome": "Biscoito Cookie Tradicional Bauducco Pacote 100g",
    "validade": "2025-07-21",
    "imagem": "https://images.openfoodfacts.org/images/products/789/196/205/4100/front_en.37.400.jpg"
  },
  {
    "codigo": "7896024761316",
    "nome": "Biscoito Recheio Limão Piraquê Pacote 76g",
    "validade": "2025-08-01",
    "imagem": "https://images.openfoodfacts.org/images/products/789/602/476/1316/front_pt.3.400.jpg"
  },
  {
    "codigo": "7896024761354",
    "nome": "BISC RECH LEITE MALT CHOCO 85G PIRAQUE",
    "validade": "2025-07-04",
    "imagem": "https://images.openfoodfacts.org/images/products/789/602/476/1354/front_pt.3.400.jpg"
  },
  {
    "codigo": "7896024720207",
    "nome": "Piraque - snack queijinho assado 100 g",
    "validade": "2025-06-06",
    "imagem": "/static/uploads/7896024720207.png"
  }
]